[
    {
        "img": "https://telegra.ph/file/665e8d882e1a0a014adc9.jpg",
        "name": "براد"
    },
    {
        "img": "https://telegra.ph/file/95fa716629e38943d06b6.jpg",
        "name": "ديمون"
    },
    {
        "img": "https://telegra.ph/file/40a7c5d14604dc57573ca.jpg",
        "name": "رينيرا"
    },
    {
        "img": "https://telegra.ph/file/30d074b088dfc27413068.jpg",
        "name": "طوكيو"
    },
    {
        "img": "https://telegra.ph/file/92beb2c729e34d337984b.jpg",
        "name": "شيلدون"
    },
    {
        "img": "https://telegra.ph/file/48d541f721d7dafab3e2a.jpg",
        "name": "باتريك"
    },
    {
        "img": "https://telegra.ph/file/383951d888280bf917b55.jpg",
        "name": "تايلر"
    },
    {
        "img": "https://telegra.ph/file/43d136e5b048a7c6f039e.jpg",
        "name": "لوك"
    },
    {
        "img": "https://telegra.ph/file/c7c09139284be8224de46.jpg",
        "name": "شارلوك"
    },
    {
        "img": "https://telegra.ph/file/da2b9aa47073c731b89c6.jpg",
        "name": "لوكي"
    },
    {
        "img": "https://telegra.ph/file/6a7dd306a6a9db84c3ed9.jpg",
        "name": "ستيف"
    },
    {
        "img": "https://telegra.ph/file/f743685beeaa6367a33f3.jpg",
        "name": "جون"
    },
    {
        "img": "https://telegra.ph/file/b8b5babcafebf993a97e6.jpg",
        "name": "ثور"
    },
    {
        "img": "https://telegra.ph/file/7c19730a1a06ff524aac0.jpg",
        "name": "اوليفر"
    },
    {
        "img": "https://telegra.ph/file/1e5e637173b0a26f68eba.jpg",
        "name": "باري"
    },
    {
        "img": "https://telegra.ph/file/55ff87fd4e3f5835582e8.jpg",
        "name": "زوم"
    },
    {
        "img": "https://telegra.ph/file/3f56ae20a29e8284fa296.jpg",
        "name": "مون نايت"
    },
    {
        "img": "https://telegra.ph/file/58758c659cee2c7161275.jpg",
        "name": "ديدبول"
    },
    {
        "img": "https://telegra.ph/file/366f3879a8280dc9684d5.jpg",
        "name": "اراجون"
    },
    {
        "img": "https://telegra.ph/file/acf2f3b96f7c33841afee.jpg",
        "name": "ليجولاس"
    },
    {
        "img": "https://telegra.ph/file/4f6ea6ebebe90537ef7ad.jpg",
        "name": "بارني"
    },
    {
        "img": "https://telegra.ph/file/8b01791a0511045063372.jpg",
        "name": "جيسي"
    },
    {
        "img": "https://telegra.ph/file/2bfd89a8c696051e5a3a1.jpg",
        "name": "ناتاشا"
    },
    {
        "img": "https://telegra.ph/file/80cc617dd364a8c691d6f.jpg",
        "name": "جون"
    },
    {
        "img": "https://telegra.ph/file/6a48ba35bd8d45737111a.jpg",
        "name": "ترافيس"
    },
    {
        "img": "https://telegra.ph/file/29bb6065c6fabd9f3c4b0.png",
        "name": "اندرو"
    },
    {
        "img": "https://telegra.ph/file/1c46a3f19439eef6aa597.jpg",
        "name": "اليوت"
    },
    {
        "img": "https://telegra.ph/file/a7977e40c59476e3aa57b.jpg",
        "name": "باتمان"
    },
    {
        "img": "https://telegra.ph/file/4cd4fa46ac3fa6f05dbc4.jpg",
        "name": "دريم"
    },
    {
        "img": "https://telegra.ph/file/9ae3ece317d24439af1e4.jpg",
        "name": "جوي"
    },
    {
        "img": "https://telegra.ph/file/0f2b6fa794c56072c937a.jpg",
        "name": "سولجر بوي"
    },
    {
        "img": "https://telegra.ph/file/c3e61baf37bf2ca2bda08.jpg",
        "name": "فرانك"
    },
    {
        "img": "https://telegra.ph/file/87f90a56c7e3f0fead6a1.jpg",
        "name": "بيتر"
    },
    {
        "img": "https://telegra.ph/file/0f7a4a13853a6f3bf9af6.jpg",
        "name": "هاوس"
    },
    {
        "img": "https://telegra.ph/file/1a29634a41199e2d1237c.jpg",
        "name": "هارفي"
    },
    {
        "img": "https://telegra.ph/file/0bf5f8cbaf88194f72993.jpg",
        "name": "مايك"
    },
    {
        "img": "https://telegra.ph/file/b50f591f15eea11a8cc91.jpg",
        "name": "دارث فيدر"
    },
    {
        "img": "https://telegra.ph/file/c939e2aa092a2aa41785f.jpg",
        "name": "كلاوس"
    },
    {
        "img": "https://telegra.ph/file/b20c7d4d47056feecc162.jpg",
        "name": "ديمون"
    },
    {
        "img": "https://telegra.ph/file/a68cd40560d4cdcbd28a4.jpg",
        "name": "ستيفن"
    },
    {
        "img": "https://telegra.ph/file/30650506ef97d1fe0110f.jpg",
        "name": "ايلايجا"
    },
    {
        "img": "https://telegra.ph/file/da96ed74e1f781dd9d8be.jpg",
        "name": "لرابط"
    },
    {
        "img": "https://telegra.ph/file/b8bfd95cd87dc214b2e4f.jpg",
        "name": "تشاندلر"
    },
    {
        "img": "https://telegra.ph/file/4e49e6fe85a673d368f5f.jpg",
        "name": "مونيكا"
    },
    {
        "img": "https://telegra.ph/file/3b878a4965db6724bec29.jpg",
        "name": "فيبي"
    },
    {
        "img": "https://telegra.ph/file/b8d5bc7f24a29d010cc68.jpg",
        "name": "ريتشل"
    },
    {
        "img": "https://telegra.ph/file/76f1be3c4f0b9bd12147d.jpg",
        "name": "روس"
    },
    {
        "img": "https://telegra.ph/file/52398e762d90730252900.jpg",
        "name": "ميشون"
    },
    {
        "img": "https://telegra.ph/file/d32adf8d50c3955b5850c.jpg",
        "name": "سول"
    },
    {
        "img": "https://telegra.ph/file/74cfb28b2656df81e165e.jpg",
        "name": "الجوكر"
    },
    {
        "img": "https://telegra.ph/file/d048f788cd954e08236f3.jpg",
        "name": "توني"
    },
    {
        "img": "https://telegra.ph/file/aa14c992bd1f1e8ebe99b.jpg",
        "name": "هاري"
    },
    {
        "img": "https://telegra.ph/file/c9463d462aafd3d4d4d69.jpg",
        "name": "كارول"
    },
    {
        "img": "https://telegra.ph/file/eb50232b3a7d2f0684ff6.jpg",
        "name": "لوسيفر"
    },
    {
        "img": "https://telegra.ph/file/4f63f780d9a98205d512b.jpg",
        "name": "اوتريد"
    },
    {
        "img": "https://telegra.ph/file/887dfcf88b3f50b9625f1.jpg",
        "name": "جاكس"
    },
    {
        "img": "https://telegra.ph/file/7b496e4c0de621b32dea9.jpg",
        "name": "والتر"
    },
    {
        "img": "https://telegra.ph/file/135635b3c98cc6e9f520e.jpg",
        "name": "راغنار"
    },
    {
        "img": "https://telegra.ph/file/ae0dac429ae33e3af09dc.jpg",
        "name": "بين لاينس"
    },
    {
        "img": "https://telegra.ph/file/28eb507ef4a7e20ca0192.jpg",
        "name": "سكوت"
    },
    {
        "img": "https://telegra.ph/file/4d8b308a545a5770ffd1f.jpg",
        "name": "سوير"
    },
    {
        "img": "https://telegra.ph/file/de9e4c82158ad9769f385.jpg",
        "name": "اليسون"
    },
    {
        "img": "https://telegra.ph/file/46d21ce1d7b2b183bc05f.jpg",
        "name": "ستايلز"
    },
    {
        "img": "https://telegra.ph/file/941b0e7f77fd56b791c5b.jpg",
        "name": "تشارلي"
    },
    {
        "img": "https://telegra.ph/file/56787c7ebd5f7505feef5.jpg",
        "name": "جاك"
    },
    {
        "img": "https://telegra.ph/file/57daa1f17ac2426492722.jpg",
        "name": "جول"
    },
    {
        "img": "https://telegra.ph/file/0843bdd47628937cf8330.jpg",
        "name": "جون سنو"
    },
    {
        "img": "https://telegra.ph/file/6f7c2a173b207364c4a16.jpg",
        "name": "توم"
    },
  {
        "img": "https://telegra.ph/file/62a9cab1f2c6f5ba8f7bc.jpg",
        "name": "ايدي"
    },
    {
        "img": "https://telegra.ph/file/883584b4017ab9bf0bc88.jpg",
        "name": "الباتشينو"
    },
    {
        "img": "https://telegra.ph/file/c6fef4d7bbcc62e0da2bf.jpg",
        "name": "بران"
    },
    {
        "img": "https://telegra.ph/file/1bad28c9e2db1f5d26aac.jpg",
        "name": "جيمي"
    },
    {
        "img": "https://telegra.ph/file/6e9951e90524b164c3613.jpg",
        "name": "اريا"
    },
  {
        "img": "https://telegra.ph/file/7e861ac4f89840d0e8171.jpg",
        "name": "تيريون"
    },
    {
        "img": "https://telegra.ph/file/561333a542ba0c33ca018.jpg",
        "name": "ايفار"
    },
    {
        "img": "https://telegra.ph/file/c1763173cf813300d1e41.jpg",
        "name": "جون ويك"
    },
    {
        "img": "https://telegra.ph/file/3ea7ae8a186c3c38fb5d8.jpg",
        "name": "تي باغ"
    },
    {
        "img": "https://telegra.ph/file/cecda57ec9fecb318e433.jpg",
        "name": "ارثر"
    },
  {
        "img": "https://telegra.ph/file/e1780c10c36e966bd4fe0.jpg",
        "name": "غاس"
    },
    {
        "img": "https://telegra.ph/file/f5a235c86a928020b9f0f.jpg",
        "name": "لوكي"
    },
    {
        "img": "https://telegra.ph/file/6bf83cae7c5aab72b1919.jpg",
        "name": "دينيرس"
    },
    {
        "img": "https://telegra.ph/file/6fa6c8cc39ccf90c26aa8.jpg",
        "name": "كريغان"
    },
    {
        "img": "https://telegra.ph/file/232a339502b63f90f53c5.jpg",
        "name": "ارثر"
    },
  {
        "img": "https://telegra.ph/file/32d9a3bdfdff5ea8c7f89.jpg",
        "name": "يوناس"
    },
    {
        "img": "https://telegra.ph/file/db6bc5d1e10d7682fd70f.jpg",
        "name": "سيرسي"
    },
    {
        "img": "https://telegra.ph/file/34a955ebff9308a545577.jpg",
        "name": "روب"
    },
    {
        "img": "https://telegra.ph/file/d99e86477ec445326a093.jpg",
        "name": "مايكل"
    },
    {
        "img": "https://telegra.ph/file/29925523f0a5c8ac9f66a.jpg",
        "name": "دين"
    },
  {
        "img": "https://telegra.ph/file/d3e89a7ed5092a14cf4c7.jpg",
        "name": "سام"
    },
    {
        "img": "https://telegra.ph/file/dbff9bbff9aaefe134e7a.jpg",
        "name": "جو"
    },
  {
        "img": "https://telegra.ph/file/c19b1a50f3b06d62eb9b4.jpg",
        "name": "نيغن"
    },
    {
        "img": "https://telegra.ph/file/41b5810f9beabd4cf5def.jpg",
        "name": "راغنار"
    },
    {
        "img": "https://telegra.ph/file/b1a3bcf68be2481714210.jpg",
        "name": "لالو"
    },
    {
        "img": "https://telegra.ph/file/4e8463bec8fa0605848d9.jpg",
        "name": "توماس"
    },
    {
        "img": "https://telegra.ph/file/6fe80eadf1ed920e902ad.jpg",
        "name": "جيرالت"
    },
  {
        "img": "https://telegra.ph/file/fee9aebbc8741c08314ec.jpg",
        "name": "هوملاندر"
    },
    {
        "img": "https://telegra.ph/file/ca080d1ad9a248760a1d9.jpg",
        "name": "بوتشر"
    },
  {
        "img": "https://telegra.ph/file/2be75bae0a21daec42d1f.jpg",
        "name": "داريل"
    },
    {
        "img": "https://telegra.ph/file/3acc30ef77438141df602.jpg",
        "name": "ماغي"
    },
    {
        "img": "https://telegra.ph/file/9c5970edd04053297efdf.jpg",
        "name": "هانيبل"
    },
    {
        "img": "https://telegra.ph/file/f620668e04839e0dc9602.jpg",
        "name": "داريك"
    },
    {
        "img": "https://telegra.ph/file/86b58434c239f55469a09.jpg",
        "name": "دوكيليان"
    },
    {
        "img": "https://telegra.ph/file/48e129b395fae77821354.jpg",
        "name": "ايموند"
    }
]
